py2chainmap.py
setup.py
test_py2chainmap.py
Py2ChainMap.egg-info/PKG-INFO
Py2ChainMap.egg-info/SOURCES.txt
Py2ChainMap.egg-info/dependency_links.txt
Py2ChainMap.egg-info/top_level.txt