Metadata-Version: 1.1
Name: Py2ChainMap
Version: 0.1.0
Summary: A backport of ChainMap from Python 3 to Python 2.
Home-page: https://github.com/kkxue/Py2ChainMap/
Author: kkxue
Author-email: xueguanwen@gmail.com
License: BSD
Platform: any
Classifier: Development Status :: 4 - Beta
Classifier: Intended Audience :: Developers
Classifier: License :: OSI Approved :: Python Software Foundation License
Classifier: Operating System :: OS Independent
Classifier: Programming Language :: Python :: 2
Classifier: Topic :: Software Development :: Libraries
Classifier: Topic :: Software Development :: Libraries :: Python Modules
Classifier: License :: OSI Approved :: BSD License
